kimtool/BaseActivity.py
kimtool/__init__.py
kimtool-0.1.0.dist-info/METADATA
kimtool-0.1.0.dist-info/WHEEL
kimtool-0.1.0.dist-info/top_level.txt
kimtool-0.1.0.dist-info/RECORD
