Metadata-Version: 2.1
Name: kimtool
Version: 0.1.0
Summary: rpa activity tool
Home-page: https://www.rpa.kingdee.com
Author: kim
Author-email: 913031410@qq.com
License: MIT Licence
Keywords: pip,rpa,kimtool,kim
Platform: any
